mini/py.typed
mini/builder/__init__.py
mini/builder/builder.py
mini/config/__init__.py
mini/config/config.py
mini/itar/README.md
mini/itar/__init__.py
mini/itar/sharded_indexed_tar.py
mini/itar/utils.py
mini/trainer/__init__.py
mini/trainer/hooks.py
mini/trainer/trainer.py
mini/trainer/utils.py
mini_kit-0.1.0.dist-info/METADATA
mini_kit-0.1.0.dist-info/WHEEL
mini_kit-0.1.0.dist-info/entry_points.txt
mini_kit-0.1.0.dist-info/RECORD
