Metadata-Version: 2.4
Name: mini-kit
Version: 0.1.0
Summary: Small self-contained micro packages for deep learning codebases.
Author-email: Karim Abou Zeid <contact@ka.codes>
Requires-Python: >=3.10
Provides-Extra: config
Requires-Dist: black>=22.1.0; extra == 'config'
Provides-Extra: itar
Requires-Dist: humanize>=4.12.3; extra == 'itar'
Requires-Dist: msgpack>=1.1.1; extra == 'itar'
Provides-Extra: trainer
Requires-Dist: pillow>=11.3.0; extra == 'trainer'
Requires-Dist: torch>=2.0.0; extra == 'trainer'
Requires-Dist: wandb>=0.20.1; extra == 'trainer'
